syngen/VERSION
syngen/__init__.py
syngen/infer.py
syngen/sdk.py
syngen/train.py
syngen/ml/__init__.py
syngen/ml/config/__init__.py
syngen/ml/config/configurations.py
syngen/ml/config/validation.py
syngen/ml/context/__init__.py
syngen/ml/context/context.py
syngen/ml/convertor/__init__.py
syngen/ml/convertor/convertor.py
syngen/ml/data_loaders/__init__.py
syngen/ml/data_loaders/data_loaders.py
syngen/ml/data_loaders/dataframe_fetcher.py
syngen/ml/flatten_json/__init__.py
syngen/ml/flatten_json/flatten_json.py
syngen/ml/handlers/__init__.py
syngen/ml/handlers/handlers.py
syngen/ml/metrics/.gitkeep
syngen/ml/metrics/__init__.py
syngen/ml/metrics/utils.py
syngen/ml/metrics/accuracy_test/__init__.py
syngen/ml/metrics/accuracy_test/accuracy_report.html
syngen/ml/metrics/accuracy_test/accuracy_test.py
syngen/ml/metrics/accuracy_test/src/main.css
syngen/ml/metrics/accuracy_test/src/script.js
syngen/ml/metrics/accuracy_test/src/fonts/OpenSans-VariableFont.ttf
syngen/ml/metrics/accuracy_test/src/img/linear-gradient.svg
syngen/ml/metrics/metrics_classes/__init__.py
syngen/ml/metrics/metrics_classes/metrics.py
syngen/ml/metrics/sample_test/__init__.py
syngen/ml/metrics/sample_test/sample_report_template.html
syngen/ml/metrics/sample_test/sample_test.py
syngen/ml/mlflow_tracker/__init__.py
syngen/ml/mlflow_tracker/mlflow_tracker.py
syngen/ml/processors/__init__.py
syngen/ml/processors/processors.py
syngen/ml/reporters/__init__.py
syngen/ml/reporters/reporters.py
syngen/ml/strategies/__init__.py
syngen/ml/strategies/strategies.py
syngen/ml/utils/__init__.py
syngen/ml/utils/utils.py
syngen/ml/vae/.gitkeep
syngen/ml/vae/__init__.py
syngen/ml/vae/models/.gitkeep
syngen/ml/vae/models/__init__.py
syngen/ml/vae/models/custom_layers.py
syngen/ml/vae/models/dataset.py
syngen/ml/vae/models/features.py
syngen/ml/vae/models/model.py
syngen/ml/vae/wrappers/__init__.py
syngen/ml/vae/wrappers/wrappers.py
syngen/ml/validation_schema/__init__.py
syngen/ml/validation_schema/validation_schema.py
syngen-0.10.32.dist-info/licenses/LICENSE
syngen-0.10.32.dist-info/METADATA
syngen-0.10.32.dist-info/WHEEL
syngen-0.10.32.dist-info/entry_points.txt
syngen-0.10.32.dist-info/top_level.txt
syngen-0.10.32.dist-info/RECORD
