Metadata-Version: 2.4
Name: syngen
Version: 0.10.32
Summary: The tool uncovers patterns, trends, and correlations hidden within your production datasets.
Home-page: https://github.com/tdspora/syngen
Author: EPAM Systems, Inc.
Maintainer: Hanna Imshenetska
License: GPLv3 License
Keywords: data,generation,synthetic,vae,tabular
Classifier: Development Status :: 5 - Production/Stable
Classifier: Operating System :: POSIX :: Linux
Classifier: Operating System :: Microsoft :: Windows
Classifier: License :: OSI Approved :: GNU General Public License v3 (GPLv3)
Classifier: Programming Language :: Python :: 3.10
Classifier: Programming Language :: Python :: 3.11
Requires-Python: <3.12,>3.9
License-File: LICENSE
Requires-Dist: aiohttp>=3.10.11
Requires-Dist: attrs
Requires-Dist: avro
Requires-Dist: base32-crockford
Requires-Dist: boto3
Requires-Dist: click
Requires-Dist: cryptography
Requires-Dist: Jinja2
Requires-Dist: keras==2.15.*
Requires-Dist: lazy==1.4
Requires-Dist: loguru
Requires-Dist: MarkupSafe==2.1.1
Requires-Dist: marshmallow==3.19.*
Requires-Dist: matplotlib==3.9.*
Requires-Dist: mlflow==3.8.*
Requires-Dist: numpy==1.26.*
Requires-Dist: openpyxl
Requires-Dist: pandas==2.2.*
Requires-Dist: pandavro==1.8.*
Requires-Dist: pathos==0.2.*
Requires-Dist: pillow==10.3.*
Requires-Dist: psutil
Requires-Dist: py-ulid
Requires-Dist: pytest
Requires-Dist: pytest-reportportal
Requires-Dist: python-slugify[unidecode]>=7.0.0
Requires-Dist: PyYAML==6.*
Requires-Dist: reportportal-client
Requires-Dist: scikit_learn==1.5.*
Requires-Dist: scipy==1.14.*
Requires-Dist: seaborn==0.13.*
Requires-Dist: setuptools==78.1.*
Requires-Dist: tensorflow==2.15.*
Requires-Dist: tornado==6.5.*
Requires-Dist: tqdm==4.66.3
Requires-Dist: Werkzeug==3.1.*
Requires-Dist: xlrd
Requires-Dist: xlwt
Provides-Extra: ui
Requires-Dist: streamlit==1.31.*; extra == "ui"
Requires-Dist: streamlit_option_menu; extra == "ui"
Dynamic: license-file
